access_parser_c
