Metadata-Version: 2.1
Name: access-parser-c
Version: 0.0.6
Summary: Access database (*.mdb, *.accdb) parser
Home-page: https://github.com/McSash/access_parser_c
Author: Sascha Saumer
Author-email: s.saumer@hotmail.de
License: UNKNOWN
Platform: UNKNOWN
Classifier: Programming Language :: Python :: 3
Classifier: License :: OSI Approved :: Apache Software License
Classifier: Operating System :: OS Independent
Requires-Python: >=3.6
License-File: LICENSE
